{
    "configurationURL": "https://soya.ownyourdata.eu/AnonymisationDemo",
    "data":[
        {
            "gehalt": 10000
        },
        {
            "gehalt": 100000
        },
        {
        },
        {
            "gehalt": 70000
        },
        {
            "gehalt": 45000
        },
        {
            "gehalt": 12000
        },
        {
        },
        {
            "gehalt": 30000
        },
        {
            "gehalt": 50000
        },
        {
            "gehalt": 20000
        },
        {
            "gehalt": 10000
        },
        {
            "gehalt": 100000
        },
        {
        },
        {
            "gehalt": 70000
        },
        {
            "gehalt": 45000
        },
        {
            "gehalt": 12000
        },
        {
        },
        {
            "gehalt": 30000
        },
        {
            "gehalt": 50000
        },
        {
            "gehalt": 20000
        }
    ]
}