{
  "version": "1.0.0",
  "valid": true,
  "anonymisedData": [
    {
      "Gehalt": "<= 25000.0"
    },
    {
      "Gehalt": ">= 47500.0"
    },
    {
      "Gehalt": "[25000.0, 47500.0]"
    },
    {
      "Gehalt": ">= 47500.0"
    },
    {
      "Gehalt": "[25000.0, 47500.0]"
    },
    {
      "Gehalt": "<= 25000.0"
    },
    {
      "Gehalt": "<= 25000.0"
    },
    {
      "Gehalt": "[25000.0, 47500.0]"
    },
    {
      "Gehalt": ">= 47500.0"
    },
    {
      "Gehalt": "<= 25000.0"
    }
  ]
}